tests/__init__.py
tests/test_datautil.py
utils_for_ds/__init__.py
utils_for_ds/data_utils.py
utils_for_ds/message.py
utils_for_ds/model_customize.py
utils_for_ds/model_train.py
utils_for_ds-0.0.16.dist-info/LICENSE
utils_for_ds-0.0.16.dist-info/METADATA
utils_for_ds-0.0.16.dist-info/WHEEL
utils_for_ds-0.0.16.dist-info/top_level.txt
utils_for_ds-0.0.16.dist-info/RECORD
